<?xml version="1.0" ?>
<annotation>
  <folder>homeobjects-voc</folder>
  <filename>living_room_1836.jpg</filename>
  <size>
    <width>1920</width>
    <height>1299</height>
    <depth>3</depth>
  </size>
  <object>
    <name>bed</name>
    <pose>Unspecified</pose>
    <truncated>0</truncated>
    <difficult>0</difficult>
    <bndbox>
      <xmin>368</xmin>
      <ymin>613</ymin>
      <xmax>1744</xmax>
      <ymax>1165</ymax>
    </bndbox>
  </object>
  <object>
    <name>table</name>
    <pose>Unspecified</pose>
    <truncated>0</truncated>
    <difficult>0</difficult>
    <bndbox>
      <xmin>1013</xmin>
      <ymin>890</ymin>
      <xmax>1462</xmax>
      <ymax>1297</ymax>
    </bndbox>
  </object>
  <object>
    <name>table</name>
    <pose>Unspecified</pose>
    <truncated>0</truncated>
    <difficult>0</difficult>
    <bndbox>
      <xmin>533</xmin>
      <ymin>919</ymin>
      <xmax>982</xmax>
      <ymax>1297</ymax>
    </bndbox>
  </object>
  <object>
    <name>lamp</name>
    <pose>Unspecified</pose>
    <truncated>0</truncated>
    <difficult>0</difficult>
    <bndbox>
      <xmin>1339</xmin>
      <ymin>463</ymin>
      <xmax>1444</xmax>
      <ymax>583</ymax>
    </bndbox>
  </object>
  <object>
    <name>lamp</name>
    <pose>Unspecified</pose>
    <truncated>0</truncated>
    <difficult>0</difficult>
    <bndbox>
      <xmin>480</xmin>
      <ymin>450</ymin>
      <xmax>584</xmax>
      <ymax>570</ymax>
    </bndbox>
  </object>
  <object>
    <name>window</name>
    <pose>Unspecified</pose>
    <truncated>0</truncated>
    <difficult>0</difficult>
    <bndbox>
      <xmin>1604</xmin>
      <ymin>257</ymin>
      <xmax>1827</xmax>
      <ymax>791</ymax>
    </bndbox>
  </object>
  <object>
    <name>potted plant</name>
    <pose>Unspecified</pose>
    <truncated>0</truncated>
    <difficult>0</difficult>
    <bndbox>
      <xmin>1296</xmin>
      <ymin>581</ymin>
      <xmax>1405</xmax>
      <ymax>742</ymax>
    </bndbox>
  </object>
  <object>
    <name>photo frame</name>
    <pose>Unspecified</pose>
    <truncated>0</truncated>
    <difficult>0</difficult>
    <bndbox>
      <xmin>786</xmin>
      <ymin>196</ymin>
      <xmax>1152</xmax>
      <ymax>487</ymax>
    </bndbox>
  </object>
</annotation>
