<?xml version="1.0" ?>
<annotation>
  <folder>homeobjects-voc</folder>
  <filename>living_room_1602.jpg</filename>
  <size>
    <width>1440</width>
    <height>1920</height>
    <depth>3</depth>
  </size>
  <object>
    <name>sofa</name>
    <pose>Unspecified</pose>
    <truncated>0</truncated>
    <difficult>0</difficult>
    <bndbox>
      <xmin>1</xmin>
      <ymin>1208</ymin>
      <xmax>899</xmax>
      <ymax>1672</ymax>
    </bndbox>
  </object>
  <object>
    <name>chair</name>
    <pose>Unspecified</pose>
    <truncated>0</truncated>
    <difficult>0</difficult>
    <bndbox>
      <xmin>911</xmin>
      <ymin>1410</ymin>
      <xmax>1230</xmax>
      <ymax>1875</ymax>
    </bndbox>
  </object>
  <object>
    <name>table</name>
    <pose>Unspecified</pose>
    <truncated>0</truncated>
    <difficult>0</difficult>
    <bndbox>
      <xmin>1</xmin>
      <ymin>1488</ymin>
      <xmax>719</xmax>
      <ymax>1918</ymax>
    </bndbox>
  </object>
  <object>
    <name>table</name>
    <pose>Unspecified</pose>
    <truncated>0</truncated>
    <difficult>0</difficult>
    <bndbox>
      <xmin>893</xmin>
      <ymin>1321</ymin>
      <xmax>1438</xmax>
      <ymax>1857</ymax>
    </bndbox>
  </object>
  <object>
    <name>potted plant</name>
    <pose>Unspecified</pose>
    <truncated>0</truncated>
    <difficult>0</difficult>
    <bndbox>
      <xmin>356</xmin>
      <ymin>1393</ymin>
      <xmax>469</xmax>
      <ymax>1574</ymax>
    </bndbox>
  </object>
  <object>
    <name>potted plant</name>
    <pose>Unspecified</pose>
    <truncated>0</truncated>
    <difficult>0</difficult>
    <bndbox>
      <xmin>264</xmin>
      <ymin>1394</ymin>
      <xmax>376</xmax>
      <ymax>1576</ymax>
    </bndbox>
  </object>
  <object>
    <name>potted plant</name>
    <pose>Unspecified</pose>
    <truncated>0</truncated>
    <difficult>0</difficult>
    <bndbox>
      <xmin>120</xmin>
      <ymin>1402</ymin>
      <xmax>232</xmax>
      <ymax>1584</ymax>
    </bndbox>
  </object>
  <object>
    <name>potted plant</name>
    <pose>Unspecified</pose>
    <truncated>0</truncated>
    <difficult>0</difficult>
    <bndbox>
      <xmin>1279</xmin>
      <ymin>1279</ymin>
      <xmax>1408</xmax>
      <ymax>1534</ymax>
    </bndbox>
  </object>
  <object>
    <name>photo frame</name>
    <pose>Unspecified</pose>
    <truncated>0</truncated>
    <difficult>0</difficult>
    <bndbox>
      <xmin>334</xmin>
      <ymin>769</ymin>
      <xmax>541</xmax>
      <ymax>934</ymax>
    </bndbox>
  </object>
  <object>
    <name>photo frame</name>
    <pose>Unspecified</pose>
    <truncated>0</truncated>
    <difficult>0</difficult>
    <bndbox>
      <xmin>943</xmin>
      <ymin>913</ymin>
      <xmax>1096</xmax>
      <ymax>1127</ymax>
    </bndbox>
  </object>
  <object>
    <name>photo frame</name>
    <pose>Unspecified</pose>
    <truncated>0</truncated>
    <difficult>0</difficult>
    <bndbox>
      <xmin>352</xmin>
      <ymin>927</ymin>
      <xmax>558</xmax>
      <ymax>1092</ymax>
    </bndbox>
  </object>
</annotation>
