<?xml version="1.0" ?>
<annotation>
  <folder>homeobjects-voc</folder>
  <filename>living_room_633.jpg</filename>
  <size>
    <width>1920</width>
    <height>1280</height>
    <depth>3</depth>
  </size>
  <object>
    <name>sofa</name>
    <pose>Unspecified</pose>
    <truncated>0</truncated>
    <difficult>0</difficult>
    <bndbox>
      <xmin>314</xmin>
      <ymin>695</ymin>
      <xmax>1116</xmax>
      <ymax>1150</ymax>
    </bndbox>
  </object>
  <object>
    <name>table</name>
    <pose>Unspecified</pose>
    <truncated>0</truncated>
    <difficult>0</difficult>
    <bndbox>
      <xmin>597</xmin>
      <ymin>876</ymin>
      <xmax>1221</xmax>
      <ymax>1278</ymax>
    </bndbox>
  </object>
  <object>
    <name>lamp</name>
    <pose>Unspecified</pose>
    <truncated>0</truncated>
    <difficult>0</difficult>
    <bndbox>
      <xmin>303</xmin>
      <ymin>371</ymin>
      <xmax>389</xmax>
      <ymax>463</ymax>
    </bndbox>
  </object>
  <object>
    <name>lamp</name>
    <pose>Unspecified</pose>
    <truncated>0</truncated>
    <difficult>0</difficult>
    <bndbox>
      <xmin>947</xmin>
      <ymin>446</ymin>
      <xmax>1009</xmax>
      <ymax>521</ymax>
    </bndbox>
  </object>
  <object>
    <name>tv</name>
    <pose>Unspecified</pose>
    <truncated>0</truncated>
    <difficult>0</difficult>
    <bndbox>
      <xmin>1119</xmin>
      <ymin>342</ymin>
      <xmax>1445</xmax>
      <ymax>610</ymax>
    </bndbox>
  </object>
  <object>
    <name>window</name>
    <pose>Unspecified</pose>
    <truncated>0</truncated>
    <difficult>0</difficult>
    <bndbox>
      <xmin>530</xmin>
      <ymin>321</ymin>
      <xmax>856</xmax>
      <ymax>608</ymax>
    </bndbox>
  </object>
</annotation>
