<?xml version="1.0" ?>
<annotation>
  <folder>homeobjects-voc</folder>
  <filename>living_room_674.jpg</filename>
  <size>
    <width>1440</width>
    <height>1920</height>
    <depth>3</depth>
  </size>
  <object>
    <name>sofa</name>
    <pose>Unspecified</pose>
    <truncated>0</truncated>
    <difficult>0</difficult>
    <bndbox>
      <xmin>95</xmin>
      <ymin>1032</ymin>
      <xmax>1437</xmax>
      <ymax>1689</ymax>
    </bndbox>
  </object>
  <object>
    <name>table</name>
    <pose>Unspecified</pose>
    <truncated>0</truncated>
    <difficult>0</difficult>
    <bndbox>
      <xmin>554</xmin>
      <ymin>1427</ymin>
      <xmax>1438</xmax>
      <ymax>1918</ymax>
    </bndbox>
  </object>
  <object>
    <name>potted plant</name>
    <pose>Unspecified</pose>
    <truncated>0</truncated>
    <difficult>0</difficult>
    <bndbox>
      <xmin>1</xmin>
      <ymin>644</ymin>
      <xmax>286</xmax>
      <ymax>1588</ymax>
    </bndbox>
  </object>
  <object>
    <name>photo frame</name>
    <pose>Unspecified</pose>
    <truncated>0</truncated>
    <difficult>0</difficult>
    <bndbox>
      <xmin>245</xmin>
      <ymin>139</ymin>
      <xmax>978</xmax>
      <ymax>870</ymax>
    </bndbox>
  </object>
  <object>
    <name>laptop</name>
    <pose>Unspecified</pose>
    <truncated>0</truncated>
    <difficult>0</difficult>
    <bndbox>
      <xmin>567</xmin>
      <ymin>1455</ymin>
      <xmax>1005</xmax>
      <ymax>1569</ymax>
    </bndbox>
  </object>
</annotation>
