<?xml version="1.0" ?>
<annotation>
  <folder>homeobjects-voc</folder>
  <filename>living_room_301.jpg</filename>
  <size>
    <width>1440</width>
    <height>1920</height>
    <depth>3</depth>
  </size>
  <object>
    <name>sofa</name>
    <pose>Unspecified</pose>
    <truncated>0</truncated>
    <difficult>0</difficult>
    <bndbox>
      <xmin>17</xmin>
      <ymin>1198</ymin>
      <xmax>572</xmax>
      <ymax>1853</ymax>
    </bndbox>
  </object>
  <object>
    <name>sofa</name>
    <pose>Unspecified</pose>
    <truncated>0</truncated>
    <difficult>0</difficult>
    <bndbox>
      <xmin>205</xmin>
      <ymin>1084</ymin>
      <xmax>577</xmax>
      <ymax>1412</ymax>
    </bndbox>
  </object>
  <object>
    <name>chair</name>
    <pose>Unspecified</pose>
    <truncated>0</truncated>
    <difficult>0</difficult>
    <bndbox>
      <xmin>1026</xmin>
      <ymin>1222</ymin>
      <xmax>1235</xmax>
      <ymax>1592</ymax>
    </bndbox>
  </object>
  <object>
    <name>chair</name>
    <pose>Unspecified</pose>
    <truncated>0</truncated>
    <difficult>0</difficult>
    <bndbox>
      <xmin>1190</xmin>
      <ymin>1315</ymin>
      <xmax>1438</xmax>
      <ymax>1776</ymax>
    </bndbox>
  </object>
  <object>
    <name>chair</name>
    <pose>Unspecified</pose>
    <truncated>0</truncated>
    <difficult>0</difficult>
    <bndbox>
      <xmin>960</xmin>
      <ymin>1161</ymin>
      <xmax>1164</xmax>
      <ymax>1475</ymax>
    </bndbox>
  </object>
  <object>
    <name>lamp</name>
    <pose>Unspecified</pose>
    <truncated>0</truncated>
    <difficult>0</difficult>
    <bndbox>
      <xmin>157</xmin>
      <ymin>1036</ymin>
      <xmax>274</xmax>
      <ymax>1155</ymax>
    </bndbox>
  </object>
  <object>
    <name>window</name>
    <pose>Unspecified</pose>
    <truncated>0</truncated>
    <difficult>0</difficult>
    <bndbox>
      <xmin>1337</xmin>
      <ymin>405</ymin>
      <xmax>1438</xmax>
      <ymax>1296</ymax>
    </bndbox>
  </object>
  <object>
    <name>photo frame</name>
    <pose>Unspecified</pose>
    <truncated>0</truncated>
    <difficult>0</difficult>
    <bndbox>
      <xmin>794</xmin>
      <ymin>492</ymin>
      <xmax>1010</xmax>
      <ymax>766</ymax>
    </bndbox>
  </object>
  <object>
    <name>photo frame</name>
    <pose>Unspecified</pose>
    <truncated>0</truncated>
    <difficult>0</difficult>
    <bndbox>
      <xmin>471</xmin>
      <ymin>660</ymin>
      <xmax>687</xmax>
      <ymax>933</ymax>
    </bndbox>
  </object>
</annotation>
