<?xml version="1.0" ?>
<annotation>
  <folder>homeobjects-voc</folder>
  <filename>living_room_822.jpg</filename>
  <size>
    <width>1920</width>
    <height>1371</height>
    <depth>3</depth>
  </size>
  <object>
    <name>sofa</name>
    <pose>Unspecified</pose>
    <truncated>0</truncated>
    <difficult>0</difficult>
    <bndbox>
      <xmin>11</xmin>
      <ymin>212</ymin>
      <xmax>1918</xmax>
      <ymax>1018</ymax>
    </bndbox>
  </object>
  <object>
    <name>table</name>
    <pose>Unspecified</pose>
    <truncated>0</truncated>
    <difficult>0</difficult>
    <bndbox>
      <xmin>1202</xmin>
      <ymin>574</ymin>
      <xmax>1817</xmax>
      <ymax>1237</ymax>
    </bndbox>
  </object>
  <object>
    <name>table</name>
    <pose>Unspecified</pose>
    <truncated>0</truncated>
    <difficult>0</difficult>
    <bndbox>
      <xmin>119</xmin>
      <ymin>621</ymin>
      <xmax>1358</xmax>
      <ymax>1315</ymax>
    </bndbox>
  </object>
  <object>
    <name>potted plant</name>
    <pose>Unspecified</pose>
    <truncated>0</truncated>
    <difficult>0</difficult>
    <bndbox>
      <xmin>1472</xmin>
      <ymin>433</ymin>
      <xmax>1597</xmax>
      <ymax>621</ymax>
    </bndbox>
  </object>
  <object>
    <name>potted plant</name>
    <pose>Unspecified</pose>
    <truncated>0</truncated>
    <difficult>0</difficult>
    <bndbox>
      <xmin>1607</xmin>
      <ymin>426</ymin>
      <xmax>1732</xmax>
      <ymax>614</ymax>
    </bndbox>
  </object>
</annotation>
