<?xml version="1.0" ?>
<annotation>
  <folder>homeobjects-voc</folder>
  <filename>living_room_136.jpg</filename>
  <size>
    <width>1920</width>
    <height>1080</height>
    <depth>3</depth>
  </size>
  <object>
    <name>sofa</name>
    <pose>Unspecified</pose>
    <truncated>0</truncated>
    <difficult>0</difficult>
    <bndbox>
      <xmin>1</xmin>
      <ymin>511</ymin>
      <xmax>463</xmax>
      <ymax>1078</ymax>
    </bndbox>
  </object>
  <object>
    <name>table</name>
    <pose>Unspecified</pose>
    <truncated>0</truncated>
    <difficult>0</difficult>
    <bndbox>
      <xmin>943</xmin>
      <ymin>660</ymin>
      <xmax>1410</xmax>
      <ymax>992</ymax>
    </bndbox>
  </object>
  <object>
    <name>lamp</name>
    <pose>Unspecified</pose>
    <truncated>0</truncated>
    <difficult>0</difficult>
    <bndbox>
      <xmin>934</xmin>
      <ymin>413</ymin>
      <xmax>1100</xmax>
      <ymax>674</ymax>
    </bndbox>
  </object>
  <object>
    <name>potted plant</name>
    <pose>Unspecified</pose>
    <truncated>0</truncated>
    <difficult>0</difficult>
    <bndbox>
      <xmin>1433</xmin>
      <ymin>265</ymin>
      <xmax>1814</xmax>
      <ymax>1009</ymax>
    </bndbox>
  </object>
  <object>
    <name>potted plant</name>
    <pose>Unspecified</pose>
    <truncated>0</truncated>
    <difficult>0</difficult>
    <bndbox>
      <xmin>1076</xmin>
      <ymin>577</ymin>
      <xmax>1147</xmax>
      <ymax>684</ymax>
    </bndbox>
  </object>
  <object>
    <name>potted plant</name>
    <pose>Unspecified</pose>
    <truncated>0</truncated>
    <difficult>0</difficult>
    <bndbox>
      <xmin>458</xmin>
      <ymin>723</ymin>
      <xmax>708</xmax>
      <ymax>1010</ymax>
    </bndbox>
  </object>
  <object>
    <name>potted plant</name>
    <pose>Unspecified</pose>
    <truncated>0</truncated>
    <difficult>0</difficult>
    <bndbox>
      <xmin>243</xmin>
      <ymin>416</ymin>
      <xmax>656</xmax>
      <ymax>800</ymax>
    </bndbox>
  </object>
  <object>
    <name>photo frame</name>
    <pose>Unspecified</pose>
    <truncated>0</truncated>
    <difficult>0</difficult>
    <bndbox>
      <xmin>674</xmin>
      <ymin>386</ymin>
      <xmax>937</xmax>
      <ymax>761</ymax>
    </bndbox>
  </object>
  <object>
    <name>photo frame</name>
    <pose>Unspecified</pose>
    <truncated>0</truncated>
    <difficult>0</difficult>
    <bndbox>
      <xmin>669</xmin>
      <ymin>28</ymin>
      <xmax>920</xmax>
      <ymax>343</ymax>
    </bndbox>
  </object>
  <object>
    <name>photo frame</name>
    <pose>Unspecified</pose>
    <truncated>0</truncated>
    <difficult>0</difficult>
    <bndbox>
      <xmin>391</xmin>
      <ymin>236</ymin>
      <xmax>653</xmax>
      <ymax>578</ymax>
    </bndbox>
  </object>
</annotation>
