<?xml version="1.0" ?>
<annotation>
  <folder>homeobjects-voc</folder>
  <filename>living_room_1p (23).jpg</filename>
  <size>
    <width>1280</width>
    <height>822</height>
    <depth>3</depth>
  </size>
  <object>
    <name>sofa</name>
    <pose>Unspecified</pose>
    <truncated>0</truncated>
    <difficult>0</difficult>
    <bndbox>
      <xmin>532</xmin>
      <ymin>163</ymin>
      <xmax>1278</xmax>
      <ymax>629</ymax>
    </bndbox>
  </object>
  <object>
    <name>chair</name>
    <pose>Unspecified</pose>
    <truncated>0</truncated>
    <difficult>0</difficult>
    <bndbox>
      <xmin>60</xmin>
      <ymin>253</ymin>
      <xmax>492</xmax>
      <ymax>785</ymax>
    </bndbox>
  </object>
  <object>
    <name>table</name>
    <pose>Unspecified</pose>
    <truncated>0</truncated>
    <difficult>0</difficult>
    <bndbox>
      <xmin>854</xmin>
      <ymin>469</ymin>
      <xmax>1278</xmax>
      <ymax>797</ymax>
    </bndbox>
  </object>
  <object>
    <name>window</name>
    <pose>Unspecified</pose>
    <truncated>0</truncated>
    <difficult>0</difficult>
    <bndbox>
      <xmin>1070</xmin>
      <ymin>2</ymin>
      <xmax>1278</xmax>
      <ymax>169</ymax>
    </bndbox>
  </object>
  <object>
    <name>window</name>
    <pose>Unspecified</pose>
    <truncated>0</truncated>
    <difficult>0</difficult>
    <bndbox>
      <xmin>773</xmin>
      <ymin>1</ymin>
      <xmax>1032</xmax>
      <ymax>169</ymax>
    </bndbox>
  </object>
  <object>
    <name>window</name>
    <pose>Unspecified</pose>
    <truncated>0</truncated>
    <difficult>0</difficult>
    <bndbox>
      <xmin>493</xmin>
      <ymin>1</ymin>
      <xmax>757</xmax>
      <ymax>175</ymax>
    </bndbox>
  </object>
</annotation>
