<?xml version="1.0" ?>
<annotation>
  <folder>homeobjects-voc</folder>
  <filename>living_room_1569.jpg</filename>
  <size>
    <width>1920</width>
    <height>1280</height>
    <depth>3</depth>
  </size>
  <object>
    <name>door</name>
    <pose>Unspecified</pose>
    <truncated>0</truncated>
    <difficult>0</difficult>
    <bndbox>
      <xmin>242</xmin>
      <ymin>70</ymin>
      <xmax>424</xmax>
      <ymax>616</ymax>
    </bndbox>
  </object>
  <object>
    <name>door</name>
    <pose>Unspecified</pose>
    <truncated>0</truncated>
    <difficult>0</difficult>
    <bndbox>
      <xmin>407</xmin>
      <ymin>59</ymin>
      <xmax>590</xmax>
      <ymax>605</ymax>
    </bndbox>
  </object>
  <object>
    <name>potted plant</name>
    <pose>Unspecified</pose>
    <truncated>0</truncated>
    <difficult>0</difficult>
    <bndbox>
      <xmin>482</xmin>
      <ymin>571</ymin>
      <xmax>736</xmax>
      <ymax>1096</ymax>
    </bndbox>
  </object>
  <object>
    <name>potted plant</name>
    <pose>Unspecified</pose>
    <truncated>0</truncated>
    <difficult>0</difficult>
    <bndbox>
      <xmin>906</xmin>
      <ymin>438</ymin>
      <xmax>1073</xmax>
      <ymax>654</ymax>
    </bndbox>
  </object>
</annotation>
