<?xml version="1.0" ?>
<annotation>
  <folder>homeobjects-voc</folder>
  <filename>living_room_1427.jpg</filename>
  <size>
    <width>1920</width>
    <height>1277</height>
    <depth>3</depth>
  </size>
  <object>
    <name>bed</name>
    <pose>Unspecified</pose>
    <truncated>0</truncated>
    <difficult>0</difficult>
    <bndbox>
      <xmin>817</xmin>
      <ymin>655</ymin>
      <xmax>1918</xmax>
      <ymax>1275</ymax>
    </bndbox>
  </object>
  <object>
    <name>table</name>
    <pose>Unspecified</pose>
    <truncated>0</truncated>
    <difficult>0</difficult>
    <bndbox>
      <xmin>659</xmin>
      <ymin>1019</ymin>
      <xmax>1421</xmax>
      <ymax>1275</ymax>
    </bndbox>
  </object>
  <object>
    <name>table</name>
    <pose>Unspecified</pose>
    <truncated>0</truncated>
    <difficult>0</difficult>
    <bndbox>
      <xmin>164</xmin>
      <ymin>938</ymin>
      <xmax>789</xmax>
      <ymax>1275</ymax>
    </bndbox>
  </object>
  <object>
    <name>lamp</name>
    <pose>Unspecified</pose>
    <truncated>0</truncated>
    <difficult>0</difficult>
    <bndbox>
      <xmin>223</xmin>
      <ymin>371</ymin>
      <xmax>439</xmax>
      <ymax>613</ymax>
    </bndbox>
  </object>
  <object>
    <name>lamp</name>
    <pose>Unspecified</pose>
    <truncated>0</truncated>
    <difficult>0</difficult>
    <bndbox>
      <xmin>798</xmin>
      <ymin>365</ymin>
      <xmax>1014</xmax>
      <ymax>607</ymax>
    </bndbox>
  </object>
  <object>
    <name>potted plant</name>
    <pose>Unspecified</pose>
    <truncated>0</truncated>
    <difficult>0</difficult>
    <bndbox>
      <xmin>434</xmin>
      <ymin>380</ymin>
      <xmax>819</xmax>
      <ymax>1039</ymax>
    </bndbox>
  </object>
  <object>
    <name>potted plant</name>
    <pose>Unspecified</pose>
    <truncated>0</truncated>
    <difficult>0</difficult>
    <bndbox>
      <xmin>986</xmin>
      <ymin>404</ymin>
      <xmax>1371</xmax>
      <ymax>1063</ymax>
    </bndbox>
  </object>
  <object>
    <name>photo frame</name>
    <pose>Unspecified</pose>
    <truncated>0</truncated>
    <difficult>0</difficult>
    <bndbox>
      <xmin>889</xmin>
      <ymin>814</ymin>
      <xmax>1163</xmax>
      <ymax>1144</ymax>
    </bndbox>
  </object>
  <object>
    <name>photo frame</name>
    <pose>Unspecified</pose>
    <truncated>0</truncated>
    <difficult>0</difficult>
    <bndbox>
      <xmin>365</xmin>
      <ymin>769</ymin>
      <xmax>575</xmax>
      <ymax>1072</ymax>
    </bndbox>
  </object>
</annotation>
