<?xml version="1.0" ?>
<annotation>
  <folder>homeobjects-voc</folder>
  <filename>living_room_933.jpg</filename>
  <size>
    <width>1080</width>
    <height>1920</height>
    <depth>3</depth>
  </size>
  <object>
    <name>sofa</name>
    <pose>Unspecified</pose>
    <truncated>0</truncated>
    <difficult>0</difficult>
    <bndbox>
      <xmin>566</xmin>
      <ymin>1202</ymin>
      <xmax>1078</xmax>
      <ymax>1547</ymax>
    </bndbox>
  </object>
  <object>
    <name>sofa</name>
    <pose>Unspecified</pose>
    <truncated>0</truncated>
    <difficult>0</difficult>
    <bndbox>
      <xmin>1</xmin>
      <ymin>1162</ymin>
      <xmax>446</xmax>
      <ymax>1507</ymax>
    </bndbox>
  </object>
  <object>
    <name>table</name>
    <pose>Unspecified</pose>
    <truncated>0</truncated>
    <difficult>0</difficult>
    <bndbox>
      <xmin>210</xmin>
      <ymin>1431</ymin>
      <xmax>1078</xmax>
      <ymax>1918</ymax>
    </bndbox>
  </object>
  <object>
    <name>table</name>
    <pose>Unspecified</pose>
    <truncated>0</truncated>
    <difficult>0</difficult>
    <bndbox>
      <xmin>189</xmin>
      <ymin>1306</ymin>
      <xmax>434</xmax>
      <ymax>1474</ymax>
    </bndbox>
  </object>
  <object>
    <name>window</name>
    <pose>Unspecified</pose>
    <truncated>0</truncated>
    <difficult>0</difficult>
    <bndbox>
      <xmin>1</xmin>
      <ymin>803</ymin>
      <xmax>160</xmax>
      <ymax>1131</ymax>
    </bndbox>
  </object>
  <object>
    <name>window</name>
    <pose>Unspecified</pose>
    <truncated>0</truncated>
    <difficult>0</difficult>
    <bndbox>
      <xmin>152</xmin>
      <ymin>834</ymin>
      <xmax>325</xmax>
      <ymax>1144</ymax>
    </bndbox>
  </object>
</annotation>
