<?xml version="1.0" ?>
<annotation>
  <folder>homeobjects-voc</folder>
  <filename>living_room_924.jpg</filename>
  <size>
    <width>1280</width>
    <height>1919</height>
    <depth>3</depth>
  </size>
  <object>
    <name>sofa</name>
    <pose>Unspecified</pose>
    <truncated>0</truncated>
    <difficult>0</difficult>
    <bndbox>
      <xmin>1</xmin>
      <ymin>210</ymin>
      <xmax>1277</xmax>
      <ymax>1163</ymax>
    </bndbox>
  </object>
  <object>
    <name>table</name>
    <pose>Unspecified</pose>
    <truncated>0</truncated>
    <difficult>0</difficult>
    <bndbox>
      <xmin>1</xmin>
      <ymin>1074</ymin>
      <xmax>1254</xmax>
      <ymax>1917</ymax>
    </bndbox>
  </object>
  <object>
    <name>potted plant</name>
    <pose>Unspecified</pose>
    <truncated>0</truncated>
    <difficult>0</difficult>
    <bndbox>
      <xmin>107</xmin>
      <ymin>285</ymin>
      <xmax>1159</xmax>
      <ymax>1408</ymax>
    </bndbox>
  </object>
</annotation>
