<?xml version="1.0" ?>
<annotation>
  <folder>homeobjects-voc</folder>
  <filename>s (154).jpg</filename>
  <size>
    <width>1280</width>
    <height>1920</height>
    <depth>3</depth>
  </size>
  <object>
    <name>table</name>
    <pose>Unspecified</pose>
    <truncated>0</truncated>
    <difficult>0</difficult>
    <bndbox>
      <xmin>141</xmin>
      <ymin>590</ymin>
      <xmax>1269</xmax>
      <ymax>1421</ymax>
    </bndbox>
  </object>
  <object>
    <name>potted plant</name>
    <pose>Unspecified</pose>
    <truncated>0</truncated>
    <difficult>0</difficult>
    <bndbox>
      <xmin>986</xmin>
      <ymin>448</ymin>
      <xmax>1153</xmax>
      <ymax>807</ymax>
    </bndbox>
  </object>
  <object>
    <name>potted plant</name>
    <pose>Unspecified</pose>
    <truncated>0</truncated>
    <difficult>0</difficult>
    <bndbox>
      <xmin>1</xmin>
      <ymin>264</ymin>
      <xmax>300</xmax>
      <ymax>954</ymax>
    </bndbox>
  </object>
</annotation>
