<?xml version="1.0" ?>
<annotation>
  <folder>homeobjects-voc</folder>
  <filename>s (382).jpg</filename>
  <size>
    <width>1920</width>
    <height>1280</height>
    <depth>3</depth>
  </size>
  <object>
    <name>chair</name>
    <pose>Unspecified</pose>
    <truncated>0</truncated>
    <difficult>0</difficult>
    <bndbox>
      <xmin>400</xmin>
      <ymin>458</ymin>
      <xmax>796</xmax>
      <ymax>1025</ymax>
    </bndbox>
  </object>
  <object>
    <name>chair</name>
    <pose>Unspecified</pose>
    <truncated>0</truncated>
    <difficult>0</difficult>
    <bndbox>
      <xmin>726</xmin>
      <ymin>578</ymin>
      <xmax>1195</xmax>
      <ymax>1204</ymax>
    </bndbox>
  </object>
  <object>
    <name>chair</name>
    <pose>Unspecified</pose>
    <truncated>0</truncated>
    <difficult>0</difficult>
    <bndbox>
      <xmin>1354</xmin>
      <ymin>556</ymin>
      <xmax>1823</xmax>
      <ymax>1182</ymax>
    </bndbox>
  </object>
  <object>
    <name>chair</name>
    <pose>Unspecified</pose>
    <truncated>0</truncated>
    <difficult>0</difficult>
    <bndbox>
      <xmin>209</xmin>
      <ymin>407</ymin>
      <xmax>530</xmax>
      <ymax>855</ymax>
    </bndbox>
  </object>
  <object>
    <name>table</name>
    <pose>Unspecified</pose>
    <truncated>0</truncated>
    <difficult>0</difficult>
    <bndbox>
      <xmin>461</xmin>
      <ymin>399</ymin>
      <xmax>1566</xmax>
      <ymax>882</ymax>
    </bndbox>
  </object>
</annotation>
